README.rst
setup.cfg
setup.py
pynuance/__init__.py
pynuance/__main__.py
pynuance/cli.py
pynuance/credentials.py
pynuance/mix.py
pynuance/nlu.py
pynuance/recorder.py
pynuance/stt.py
pynuance/tts.py
pynuance/websocket.py
pynuance.egg-info/PKG-INFO
pynuance.egg-info/SOURCES.txt
pynuance.egg-info/dependency_links.txt
pynuance.egg-info/entry_points.txt
pynuance.egg-info/requires.txt
pynuance.egg-info/top_level.txt
pynuance/libs/common.py
pynuance/libs/error.py
pynuance/libs/languages.py
pynuance/libs/nuance_http.py